LICENSE
MANIFEST.in
README.md
requirements.txt
setup.cfg
setup.py
overload_function/__init__.py
overload_function/overload.py
overload_function.egg-info/PKG-INFO
overload_function.egg-info/SOURCES.txt
overload_function.egg-info/dependency_links.txt
overload_function.egg-info/top_level.txt