Metadata-Version: 1.1
Name: overload-function
Version: 1.2.0
Summary: Library to overload function and methods like C++. This library tries to match type annotations.
Home-page: https://github.com/HashSplat/overload_function
Author: Justin Engel
Author-email: jtengel08@gmail.com
License: MIT
Download-URL: https://github.com/HashSplat/overload_function/archive/v1.2.0.tar.gz
Keywords: overload,overload function,overload method
Platform: any
Classifier: Programming Language :: Python
Classifier: Programming Language :: Python :: 3
Classifier: Operating System :: OS Independent
